jupyterlab_ws_chat/__init__.py
jupyterlab_ws_chat/_version.py
jupyterlab_ws_chat/config_manager.py
jupyterlab_ws_chat/extension.py
jupyterlab_ws_chat/handlers.py
jupyterlab_ws_chat/models.py
jupyterlab_ws_chat/config/config_schema.json
jupyterlab_ws_chat-0.5.1.data/data/etc/jupyter/jupyter_server_config.d/jupyterlab_ws_chat.json
jupyterlab_ws_chat-0.5.1.data/data/share/jupyter/labextensions/jupyterlab-ws-chat-extension/package.json
jupyterlab_ws_chat-0.5.1.data/data/share/jupyter/labextensions/jupyterlab-ws-chat-extension/schemas/jupyterlab-ws-chat-extension/chat.json
jupyterlab_ws_chat-0.5.1.data/data/share/jupyter/labextensions/jupyterlab-ws-chat-extension/schemas/jupyterlab-ws-chat-extension/package.json.orig
jupyterlab_ws_chat-0.5.1.data/data/share/jupyter/labextensions/jupyterlab-ws-chat-extension/static/367.a48bd4bbcbf36d31b8a9.js
jupyterlab_ws_chat-0.5.1.data/data/share/jupyter/labextensions/jupyterlab-ws-chat-extension/static/367.a48bd4bbcbf36d31b8a9.js.LICENSE.txt
jupyterlab_ws_chat-0.5.1.data/data/share/jupyter/labextensions/jupyterlab-ws-chat-extension/static/698.13edf2bec86dc7453644.js
jupyterlab_ws_chat-0.5.1.data/data/share/jupyter/labextensions/jupyterlab-ws-chat-extension/static/728.7dc7b1f7119db4182ec7.js
jupyterlab_ws_chat-0.5.1.data/data/share/jupyter/labextensions/jupyterlab-ws-chat-extension/static/remoteEntry.f3499b3dc9cedf19dc86.js
jupyterlab_ws_chat-0.5.1.data/data/share/jupyter/labextensions/jupyterlab-ws-chat-extension/static/style.js
jupyterlab_ws_chat-0.5.1.data/data/share/jupyter/labextensions/jupyterlab-ws-chat-extension/static/third-party-licenses.json
jupyterlab_ws_chat-0.5.1.data/data/share/jupyter/labextensions/jupyterlab-ws-chat-extension/install.json
jupyterlab_ws_chat-0.5.1.dist-info/METADATA
jupyterlab_ws_chat-0.5.1.dist-info/WHEEL
jupyterlab_ws_chat-0.5.1.dist-info/licenses/LICENSE
jupyterlab_ws_chat-0.5.1.dist-info/RECORD
