Metadata-Version: 2.4
Name: jupyterlab_ws_chat
Version: 0.5.1
Dynamic: Keywords
Summary: A chat extension for Jupyterlab, based on websocket
Project-URL: Homepage, https://github.com/brichet/jupyterlab-ws-chat
Project-URL: Bug Tracker, https://github.com/brichet/jupyterlab-ws-chat/issues
Project-URL: Repository, https://github.com/brichet/jupyterlab-ws-chat.git
Author-email: Jupyter Development Team <jupyter@googlegroups.com>
License: BSD 3-Clause License
License-File: LICENSE
Classifier: Framework :: Jupyter
Classifier: Framework :: Jupyter :: JupyterLab
Classifier: Framework :: Jupyter :: JupyterLab :: 4
Classifier: Framework :: Jupyter :: JupyterLab :: Extensions
Classifier: Framework :: Jupyter :: JupyterLab :: Extensions :: Prebuilt
Classifier: License :: OSI Approved :: BSD License
Classifier: Programming Language :: Python
Classifier: Programming Language :: Python :: 3
Classifier: Programming Language :: Python :: 3.8
Classifier: Programming Language :: Python :: 3.9
Classifier: Programming Language :: Python :: 3.10
Classifier: Programming Language :: Python :: 3.11
Classifier: Programming Language :: Python :: 3.12
Requires-Python: >=3.8
Requires-Dist: deepmerge>=1.0
Requires-Dist: jupyter-server<3,>=2.0.1
Requires-Dist: jupyterlab~=4.0
Requires-Dist: pydantic>=2
Requires-Dist: traitlets>=5.0
Provides-Extra: test
Requires-Dist: coverage; extra == 'test'
Requires-Dist: pytest; extra == 'test'
Requires-Dist: pytest-asyncio; extra == 'test'
Requires-Dist: pytest-cov; extra == 'test'
Requires-Dist: pytest-jupyter[server]>=0.6.0; extra == 'test'
